snuff_utils/.python_version
snuff_utils/DottedDict.py
snuff_utils/HashableDict.py
snuff_utils/MongoAggregation.py
snuff_utils/MongoMatchFilter.py
snuff_utils/__init__.py
snuff_utils/date_and_time.py
snuff_utils/decorators.py
snuff_utils/dict_functions.py
snuff_utils/file_functions.py
snuff_utils/flask_decorators.py
snuff_utils/graceful_exit.py
snuff_utils/io_utils.py
snuff_utils/iterators.py
snuff_utils/jsonschema_patterns.py
snuff_utils/list_of_dicts.py
snuff_utils/marshmallow_extras.py
snuff_utils/mongo_aggregation_patterns.py
snuff_utils/mongoengine_extras.py
snuff_utils/nested_defaultdict.py
snuff_utils/sorting.py
snuff_utils/string_functions.py
snuff_utils/timer.py
snuff_utils/unittests_sorting.py
snuff_utils/universal.py
snuff_utils/xml_etree_extras.py
snuff_utils/sqlalchemy_extras/__init__.py
snuff_utils/sqlalchemy_extras/custom_column.py
snuff_utils/sqlalchemy_extras/custom_query.py
snuff_utils/yandex_mailer/YandexMailer.py
snuff_utils/yandex_mailer/__init__.py
snuff_utils/yandex_mailer/config.py
snuff_utils-1.0.2.dist-info/METADATA
snuff_utils-1.0.2.dist-info/WHEEL
snuff_utils-1.0.2.dist-info/top_level.txt
snuff_utils-1.0.2.dist-info/RECORD
