Metadata-Version: 2.1
Name: snuff-utils
Version: 1.0.2
Summary: Universal functions and decorators and some packages extras
Home-page: https://github.com/egorgvo/utils
Author: Egor Gvo
Author-email: work.egvo@ya.ru
License: MIT
Platform: UNKNOWN
Classifier: License :: OSI Approved :: MIT License
Classifier: Programming Language :: Python :: 3
